cdktf_gke_auth/__init__.py
cdktf_gke_auth/py.typed
cdktf_gke_auth/_jsii/__init__.py
cdktf_gke_auth/_jsii/cdktf-gke-auth@1.1.1.jsii.tgz
cdktf_gke_auth-1.1.1.dist-info/LICENSE
cdktf_gke_auth-1.1.1.dist-info/METADATA
cdktf_gke_auth-1.1.1.dist-info/WHEEL
cdktf_gke_auth-1.1.1.dist-info/top_level.txt
cdktf_gke_auth-1.1.1.dist-info/RECORD
