Metadata-Version: 2.1
Name: cdktf-gke-auth
Version: 1.1.1
Summary: cdktf-gke-auth
Home-page: https://github.com/01walid/cdktf-gke-auth.git
Author: Walid Ziouche<hi@walid.dev>
License: Apache-2.0
Project-URL: Source, https://github.com/01walid/cdktf-gke-auth.git
Classifier: Intended Audience :: Developers
Classifier: Operating System :: OS Independent
Classifier: Programming Language :: JavaScript
Classifier: Programming Language :: Python :: 3 :: Only
Classifier: Programming Language :: Python :: 3.7
Classifier: Programming Language :: Python :: 3.8
Classifier: Programming Language :: Python :: 3.9
Classifier: Programming Language :: Python :: 3.10
Classifier: Programming Language :: Python :: 3.11
Classifier: Typing :: Typed
Classifier: Development Status :: 5 - Production/Stable
Classifier: License :: OSI Approved
Requires-Python: ~=3.7
License-File: LICENSE
Requires-Dist: cdktf-cdktf-provider-google (<8.0.0,>=7.0.0)
Requires-Dist: cdktf (<0.17.0,>=0.16.0)
Requires-Dist: constructs (<10.3.0,>=10.2.0)
Requires-Dist: jsii (<2.0.0,>=1.82.0)
Requires-Dist: publication (>=0.0.3)
Requires-Dist: typeguard (~=2.13.3)
